fhir_utils/__init__.py
fhir_utils/conf.py
fhir_utils/version.py
fhir_utils-0.0.1a0.dist-info/LICENSE
fhir_utils-0.0.1a0.dist-info/METADATA
fhir_utils-0.0.1a0.dist-info/WHEEL
fhir_utils-0.0.1a0.dist-info/entry_points.txt
fhir_utils-0.0.1a0.dist-info/RECORD
